orbie-1.0.0.dist-info/METADATA
orbie-1.0.0.dist-info/WHEEL
orbie-1.0.0.dist-info/entry_points.txt
orbie-1.0.0.dist-info/licenses/LICENSE
orbie/__init__.py
orbie/orbie.py
orbie-1.0.0.dist-info/RECORD
