Metadata-Version: 2.1
Name: orbie
Version: 1.0.0
Summary: A checker to restrict the tangling of import interdependencies
Author-Email: Michael Ho <michael.ho@ieee.org>
License: MIT
Requires-Python: >=3.12
Requires-Dist: importlab>=0.8.1
